vigi/__init__.py
vigi/app.py
vigi/auth.py
vigi/cache.py
vigi/camera_config.py
vigi/camera_monitor.py
vigi/cli.py
vigi/configuration_manager.py
vigi/context_processors.py
vigi/database.py
vigi/motion_detector.py
vigi/notifier.py
vigi/video_recorder.py
vigi/notification_providers/__init__.py
vigi/notification_providers/email_notification_provider.py
vigi/notification_providers/sms_notification_provider.py
vigi/routes/__init__.py
vigi/routes/camera.py
vigi/routes/live.py
vigi/routes/recordings.py
vigi/static/android-chrome-192x192.png
vigi/static/android-chrome-512x512.png
vigi/static/apple-touch-icon.png
vigi/static/favicon-16x16.png
vigi/static/favicon-32x32.png
vigi/static/favicon.ico
vigi/static/logo.png
vigi/static/main.js
vigi/static/no_preview_available.jpg
vigi/static/site.webmanifest
vigi/static/style.css
vigi/templates/base.html
vigi/templates/live/index.html
vigi/templates/recordings/index.html
vigi/utils/drawing.py
vigi/utils/fps_calculator.py
vigi/utils/media.py
vigi/utils/pub_sub.py
vigi/utils/spatial.py
vigi-0.9.2.dist-info/METADATA
vigi-0.9.2.dist-info/WHEEL
vigi-0.9.2.dist-info/entry_points.txt
vigi-0.9.2.dist-info/licenses/LICENSE
vigi-0.9.2.dist-info/RECORD
