Metadata-Version: 2.3
Name: vigi
Version: 0.9.2
Summary: Camera surveillance system with motion detection and object recognition for home security.
Project-URL: Homepage, https://github.com/plashchynski/vigi
Project-URL: Repository, https://github.com/plashchynski/vigi.git
Project-URL: Issues, https://github.com/plashchynski/vigi/issues
Project-URL: Changelog, https://github.com/plashchynski/vigi/blob/main/CHANGELOG.md
Project-URL: Documentation, https://github.com/plashchynski/vigi/blob/docs/
Author-email: Dzmitry Plashchynski <plashchynski@gmail.com>
Maintainer-email: Dzmitry Plashchynski <plashchynski@gmail.com>
License-File: LICENSE
Keywords: camera,home security,motion detection,object recognition,surveillance
Classifier: Development Status :: 4 - Beta
Classifier: License :: OSI Approved :: MIT License
Classifier: Operating System :: OS Independent
Classifier: Programming Language :: Python :: 3
Requires-Python: >=3.8
Requires-Dist: bootstrap-flask==2.3.3
Requires-Dist: flask-caching==2.1.0
Requires-Dist: flask-httpauth==4.8.0
Requires-Dist: flask==3.0.2
Requires-Dist: humanize==4.9.0
Requires-Dist: opencv-python==4.9.0.80
Requires-Dist: platformdirs==4.2.0
Requires-Dist: twilio==9.0.2
Requires-Dist: ultralytics==8.1.30
